COPYRIGHT
LICENSE
MANIFEST.in
README
hgshelve.py
setup.cfg
setup.py
test-shelve
test-shelve-color
test-shelve-color.out
test-shelve.out
hgshelve.egg-info/PKG-INFO
hgshelve.egg-info/SOURCES.txt
hgshelve.egg-info/dependency_links.txt
hgshelve.egg-info/requires.txt
hgshelve.egg-info/top_level.txt