Metadata-Version: 1.1
Name: hgshelve
Version: 0.1
Summary: Shelve Extension for Mercurial
Home-page: https://bitbucket.org/tksoh/hgshelve
Author: TK Soh
Author-email: teekaysoh@gmail.com
License: GPL-2
Download-URL: http://mercurial.selenic.com/wiki/ShelveExtension
Platform: UNKNOWN
Classifier: Development Status :: 5 - Production/Stable
Classifier: Environment :: Plugins
Classifier: Intended Audience :: Developers
Classifier: License :: OSI Approved :: GNU General Public License (GPL)
Classifier: Operating System :: OS Independent
Classifier: Programming Language :: Python
Classifier: Topic :: Software Development :: Version Control
